diary_md/__init__.py
diary_md/_version.py
diary_md/exceptions.py
diary_md/exchange.py
diary_md/git.py
diary_md/models.py
diary_md/parser.py
diary_md/cli/__init__.py
diary_md/cli/digest.py
diary_md/cli/reconcile.py
diary_md/cli/update.py
diary_md-0.1.1.dist-info/METADATA
diary_md-0.1.1.dist-info/WHEEL
diary_md-0.1.1.dist-info/entry_points.txt
diary_md-0.1.1.dist-info/licenses/LICENSE
diary_md-0.1.1.dist-info/RECORD
