Metadata-Version: 2.4
Name: diary-md
Version: 0.1.1
Summary: Tools for managing markdown-based diary entries
Project-URL: Repository, https://github.com/tobixen/diary-md
Project-URL: Issues, https://github.com/tobixen/diary-md/issues
Author-email: Tobias Brox <tobias@redpill-linpro.com>
License-Expression: AGPL-3.0-or-later
License-File: LICENSE
Classifier: Development Status :: 4 - Beta
Classifier: Intended Audience :: End Users/Desktop
Classifier: License :: OSI Approved :: GNU Affero General Public License v3 or later (AGPLv3+)
Classifier: Programming Language :: Python :: 3
Classifier: Programming Language :: Python :: 3.10
Classifier: Programming Language :: Python :: 3.11
Classifier: Programming Language :: Python :: 3.12
Classifier: Programming Language :: Python :: 3.13
Classifier: Programming Language :: Python :: 3.14
Requires-Python: >=3.10
Requires-Dist: click>=8.0
Provides-Extra: dev
Requires-Dist: pre-commit>=4.0; extra == 'dev'
Requires-Dist: pytest-cov; extra == 'dev'
Requires-Dist: pytest>=8.0; extra == 'dev'
Requires-Dist: ruff>=0.14; extra == 'dev'
